{
    "dataList":[
    	{
        	"time":"2018.03.23",
        	"title":"实现鼠标经过图片一道光闪过效果",
        	"img":"http://pic1.win4000.com/wallpaper/7/53d8c04c93acd.jpg",
        	"url":"example/2018-03-23.html",
        	"content":"实例中的闪光颜色可以自己修改，倾斜角度也可以调，这个效果的实现方式也挺简单的，主要是通过transition过渡属性和linear-gradient属性实现的。"
        },
        {
        	"time":"2018.03.22",
        	"title":"使用css3新特性实现纸张边角卷起效果",
        	"img":"http://pic1.win4000.com/wallpaper/b/59449293c86d1.jpg",
        	"url":"example/2018-03-22.html",
        	"content":"这篇是第一个实例，而且还是以前无聊的时候，逛论坛发现的，说不定以后会用到，就跟着写了一遍。效果实现方式：主要使用了filter属性和linear-gradient属性。F12直接查看实现方式"
        }
    ]
}